{
    "properties": [
        {
            "sourceType": "com.github.rwocj.wx.properties.WxProperties",
            "name": "wx.appId",
            "type": "java.lang.String",
            "description": "应用appId.",
            "required": true
        },
        {
            "sourceType": "com.github.rwocj.wx.properties.WxPayProperties",
            "name": "wx.pay.mch-id",
            "type": "java.lang.String",
            "description": "微信支付商户id.",
            "required": true
        },
        {
            "sourceType": "com.github.rwocj.wx.properties.WxPayProperties",
            "name": "wx.pay.certificate-serial-no",
            "type": "java.lang.String",
            "required": true,
            "description": "微信支付证书序列号."
        },
        {
            "sourceType": "com.github.rwocj.wx.properties.WxPayProperties",
            "name": "wx.pay.api-v3-key",
            "type": "java.lang.String",
            "required": true,
            "description": "v3接口密钥."
        },
        {
            "sourceType": "com.github.rwocj.wx.properties.WxPayProperties",
            "name": "wx.pay.private-key-path",
            "type": "java.lang.String",
            "required": true,
            "description": "微信支付私钥文件路径，如classpath:/cert/app.pem."
        },
        {
            "sourceType": "com.github.rwocj.wx.properties.WxPayProperties",
            "name": "wx.pay.notify-url",
            "type": "java.lang.String",
            "required": true,
            "description": "支付通知url."
        },
        {
            "sourceType": "com.github.rwocj.wx.properties.WxPayProperties",
            "name": "wx.pay.refund-notify-url",
            "type": "java.lang.String",
            "required": true,
            "description": "退款通知url."
        }
    ]
}
